<?xml version="1.0" encoding="UTF-8"?>
<objects serializationModel="Studio.02.02.00">
	<object class="ParameterPreset" id="{dbfc0922-95cc-484a-8e51-67ecad558130}">
		<property name="name">
			<value>Parameter 1</value>
		</property>
		<relationship name="folder">
			<destination>{3aae6996-344a-4518-81ec-b2e040cd75b2}</destination>
		</relationship>
		<relationship name="parameter">
			<destination>{8edd33a8-4826-47f6-9687-154603417ffa}</destination>
		</relationship>
	</object>
	<object class="GameParameter" id="{8edd33a8-4826-47f6-9687-154603417ffa}">
		<property name="initialValue">
			<value>0</value>
		</property>
	</object>
</objects>
